pydev_utils/__init__.py
pydev_utils/ufmt_wrapper.py
pydev_utils-0.0.1.dist-info/METADATA
pydev_utils-0.0.1.dist-info/WHEEL
pydev_utils-0.0.1.dist-info/top_level.txt
pydev_utils-0.0.1.dist-info/RECORD
