Metadata-Version: 2.1
Name: pydev-utils
Version: 0.0.1
Summary: a package with some developer tools
Home-page: UNKNOWN
License: UNKNOWN
Platform: UNKNOWN
Provides-Extra: all
Requires-Dist: black (~=21.11b1) ; extra == 'all'
Requires-Dist: ufmt (~=1.3.0) ; extra == 'all'
Requires-Dist: usort (~=0.6.4) ; extra == 'all'
Provides-Extra: ufmt_wrapper
Requires-Dist: black (~=21.11b1) ; extra == 'ufmt_wrapper'
Requires-Dist: ufmt (~=1.3.0) ; extra == 'ufmt_wrapper'
Requires-Dist: usort (~=0.6.4) ; extra == 'ufmt_wrapper'
